postalcodes_ni/__init__.py
postalcodes_ni/_codes.py
postalcodes_ni/exceptions.py
postalcodes_ni/postalcodes.py
postalcodes_ni-1.2.0.dist-info/AUTHORS.md
postalcodes_ni-1.2.0.dist-info/LICENSE
postalcodes_ni-1.2.0.dist-info/METADATA
postalcodes_ni-1.2.0.dist-info/WHEEL
postalcodes_ni-1.2.0.dist-info/top_level.txt
postalcodes_ni-1.2.0.dist-info/RECORD
