Metadata-Version: 2.1
Name: postalcodes-ni
Version: 1.2.0
Summary: Python package for handle Nicaragua postal codes
Home-page: https://github.com/oscarmcm/postalcodes-ni
Author: Oscar Cortez
Author-email: om.cortez.2010@gmail.com
License: MIT license
Project-URL: Documentation, https://postalcodes-ni.readthedocs.io
Project-URL: Funding, https://donate.pypi.org
Project-URL: Say Thanks!, http://saythanks.io/to/oscarmcm
Project-URL: Source, https://github.com/oscarmcm/postalcodes-ni/
Project-URL: Tracker, https://github.com/oscarmcm/postalcodes-ni/issues
Keywords: postalcodes nicaragua
Platform: UNKNOWN
Classifier: Development Status :: 5 - Production/Stable
Classifier: Intended Audience :: Developers
Classifier: Topic :: Software Development :: Libraries
Classifier: License :: OSI Approved :: MIT License
Classifier: Natural Language :: English
Classifier: Natural Language :: Spanish
Classifier: Programming Language :: Python :: 3
Classifier: Programming Language :: Python :: 3.4
Classifier: Programming Language :: Python :: 3.5
Classifier: Programming Language :: Python :: 3.6
Classifier: Programming Language :: Python :: 3.7
Requires-Python: >=3
